Custom_Widgets/AnalogGaugeWidget.py
Custom_Widgets/ProgressIndicator.py
Custom_Widgets/ProjectMaker.py
Custom_Widgets/QAppSettings.py
Custom_Widgets/QCustomCheckBox.py
Custom_Widgets/QCustomProgressIndicator.py
Custom_Widgets/QCustomQPushButton.py
Custom_Widgets/QCustomQPushButtonGroup.py
Custom_Widgets/QCustomQSlider.py
Custom_Widgets/QCustomQStackedWidget.py
Custom_Widgets/QCustomSlideMenu.py
Custom_Widgets/RoundProgressBar.py
Custom_Widgets/SpiralProgressBar.py
Custom_Widgets/Widgets.py
Custom_Widgets/WidgetsWorker.py
Custom_Widgets/__init__.py
Custom_Widgets/interface.ui
Custom_Widgets/main.py
Custom_Widgets/ProgressIndicator/__init__.py
Custom_Widgets/ProgressIndicator/interface.ui
Custom_Widgets/ProgressIndicator/test.py
Custom_Widgets/ProgressIndicator/ui_interface.py
Custom_Widgets/ProgressIndicator/__pycache__/__init__.cpython-310.pyc
Custom_Widgets/ProgressIndicator/__pycache__/__init__.cpython-38.pyc
Custom_Widgets/ProgressIndicator/__pycache__/test.cpython-310.pyc
Custom_Widgets/ProgressIndicator/__pycache__/test.cpython-38.pyc
Custom_Widgets/ProgressIndicator/__pycache__/ui_interface.cpython-310.pyc
Custom_Widgets/ProgressIndicator/__pycache__/ui_interface.cpython-38.pyc
Custom_Widgets/ProgressIndicator/__pycache__/ui_interface.cpython-39.pyc
Custom_Widgets/Qss/QSS_Resources.qrc
Custom_Widgets/Qss/SassCompiler.py
Custom_Widgets/Qss/SvgToPngIcons.py
Custom_Widgets/Qss/__init__.py
Custom_Widgets/Qss/_styles.scss
Custom_Widgets/Qss/colorsystem.py
Custom_Widgets/Qss/main.scss
Custom_Widgets/Qss/__pycache__/QSS_Resources.cpython-39.pyc
Custom_Widgets/Qss/__pycache__/SassCompiler.cpython-310.pyc
Custom_Widgets/Qss/__pycache__/SassCompiler.cpython-311.pyc
Custom_Widgets/Qss/__pycache__/SassCompiler.cpython-38.pyc
Custom_Widgets/Qss/__pycache__/SvgToPngIcons.cpython-310.pyc
Custom_Widgets/Qss/__pycache__/SvgToPngIcons.cpython-311.pyc
Custom_Widgets/Qss/__pycache__/SvgToPngIcons.cpython-38.pyc
Custom_Widgets/Qss/__pycache__/SvgToPngIcons.cpython-39.pyc
QT_PyQt_PySide_Custom_Widgets-0.6.8.dist-info/LICENSE
QT_PyQt_PySide_Custom_Widgets-0.6.8.dist-info/METADATA
QT_PyQt_PySide_Custom_Widgets-0.6.8.dist-info/WHEEL
QT_PyQt_PySide_Custom_Widgets-0.6.8.dist-info/top_level.txt
QT_PyQt_PySide_Custom_Widgets-0.6.8.dist-info/RECORD
