Metadata-Version: 2.1
Name: QT-PyQt-PySide-Custom-Widgets
Version: 0.6.8
Summary: Custom widgets and widget animations made for QT applications
Home-page: https://github.com/KhamisiKibet/QT-PyQt-PySide-Custom-Widgets
Download-URL: https://github.com/KhamisiKibet/QT-PyQt-PySide-Custom-Widgets/archive/refs/heads/main.zip
Author: Khamisi Kibet
Author-email: kibetkhamisi@gmail.com
License: GNU General Public License v3.0
Keywords: PySide,PyQt,animation,custom,widgets,QML,C++,QT Creator,Moder GUI,Desktop GUI,Design
Classifier: Development Status :: 3 - Alpha
Classifier: Intended Audience :: Developers
Classifier: Topic :: Software Development :: Build Tools
Classifier: License :: OSI Approved :: MIT License
Classifier: Programming Language :: Python :: 3.6
Classifier: Programming Language :: Python :: 3.7
Classifier: Programming Language :: Python :: 3.8
Classifier: Programming Language :: Python :: 3.9
Classifier: Programming Language :: Python :: 3.10
Classifier: Programming Language :: Python :: 3.11
License-File: LICENSE
Requires-Dist: qtpy
Requires-Dist: cairosvg
Requires-Dist: qtsass
Requires-Dist: matplotlib
Requires-Dist: mock
